cube_to_rag/__init__.py
cube_to_rag/core/__init__.py
cube_to_rag/core/config.py
cube_to_rag/core/llm.py
cube_to_rag/core/schema_embeddings.py
cube_to_rag/models/__init__.py
cube_to_rag/models/chat.py
cube_to_rag/tools/__init__.py
cube_to_rag/tools/cube_graphql_tool.py
cube_to_rag/tools/cube_graphql_wrapper.py
cube_to_rag/tools/cube_schema_tool.py
cube_to_rag/tools/milvus_helper.py
cube_to_rag/tools/vector_search_tool.py
cube_to_rag-0.1.0a1.dist-info/METADATA
cube_to_rag-0.1.0a1.dist-info/WHEEL
cube_to_rag-0.1.0a1.dist-info/entry_points.txt
cube_to_rag-0.1.0a1.dist-info/RECORD
