Metadata-Version: 2.4
Name: cube-to-rag
Version: 0.1.0a1
Summary: RAG system for Cube.js analytics with vector search capabilities
Requires-Python: >=3.11,<4.0
Classifier: Programming Language :: Python :: 3
Classifier: Programming Language :: Python :: 3.11
Classifier: Programming Language :: Python :: 3.12
Classifier: Programming Language :: Python :: 3.13
Classifier: Programming Language :: Python :: 3.14
Requires-Dist: fastapi (>=0.115.0,<0.116.0)
Requires-Dist: gql (>=3.5.0,<4.0.0)
Requires-Dist: itsdangerous (>=2.1.2,<3.0.0)
Requires-Dist: jinja2 (>=3.1.2,<4.0.0)
Requires-Dist: langchain (>=0.3.7,<0.4.0)
Requires-Dist: langchain-anthropic (>=0.2.4,<0.3.0)
Requires-Dist: langchain-aws (>=0.2.6,<0.3.0)
Requires-Dist: langchain-community (>=0.3.7,<0.4.0)
Requires-Dist: langchain-milvus (>=0.1.5,<0.2.0)
Requires-Dist: langchain-openai (>=0.2.8,<0.3.0)
Requires-Dist: psycopg2-binary (>=2.9.9,<3.0.0)
Requires-Dist: pydantic (>=2.9.2,<3.0.0)
Requires-Dist: pydantic-settings (>=2.6.0,<3.0.0)
Requires-Dist: pyjwt (>=2.8.0,<3.0.0)
Requires-Dist: pymilvus (>=2.4.0,<3.0.0)
Requires-Dist: python-dotenv (>=1.0.1,<2.0.0)
Requires-Dist: requests (>=2.32.3,<3.0.0)
Requires-Dist: uvicorn[standard] (>=0.32.0,<0.33.0)
